<ARTIKEL><AUSTAUSCH_STEUERUNG><AUSTAUSCH_ID>13PSPPSARTIKEL20240426287843</AUSTAUSCH_ID><LIEFERUNGSTYP>NEU</LIEFERUNGSTYP><LIEFERANT_TYP>TIMCHANNEL</LIEFERANT_TYP><LIEFERANT>TIMCHANNEL</LIEFERANT><RFA_LISTE><RFA>WDR</RFA></RFA_LISTE><VERARBEITUNGSSTATUS><DATUM>20240426</DATUM><UHRZEIT>134936</UHRZEIT><XMLERZEUGER>TIMCHANNEL</XMLERZEUGER></VERARBEITUNGSSTATUS></AUSTAUSCH_STEUERUNG><METADATEN><EXTERNE_ARTIKEL_ID>20240426287843</EXTERNE_ARTIKEL_ID><ERSCHEINUNGSDATUM>20240426</ERSCHEINUNGSDATUM><ERFASSUNGSDATUM></ERFASSUNGSDATUM><QUELLE><AUSTAUSCH_KUERZEL>BI</AUSTAUSCH_KUERZEL><ARTIKELSPRACH_LISTE></ARTIKELSPRACH_LISTE><AUSTAUSCH_NAME>Bild</AUSTAUSCH_NAME><HERKUNFT>DATASCAN</HERKUNFT></QUELLE><KLASSIFIKATIONSLISTE></KLASSIFIKATIONSLISTE><PERSONENLISTE></PERSONENLISTE><DESKRIPTORENLISTE></DESKRIPTORENLISTE><SACHGEBIETSLISTE></SACHGEBIETSLISTE><GATTUNGSLISTE></GATTUNGSLISTE><EXTERNE_INDEXATE></EXTERNE_INDEXATE><VERLAGSEIGENE_KLASSIFIZIERUNG><VERSCHLAGWORTUNGSLISTE></VERSCHLAGWORTUNGSLISTE><VERLAG_METARESSORT_LISTE></VERLAG_METARESSORT_LISTE></VERLAGSEIGENE_KLASSIFIZIERUNG><ARD_RESSORT_LISTE></ARD_RESSORT_LISTE><PRAESENTATIONSFORM_LISTE></PRAESENTATIONSFORM_LISTE><BEZUGSDOKUMENT><BEZUGSDOKUMENT_NUMMER>20240426_12Uhr</BEZUGSDOKUMENT_NUMMER></BEZUGSDOKUMENT><ARTIKEL_IMAGE><DATEINAME>/timFileSys/timchannel/dockerlocl/imagestore/Pressespiegel/2024/04/26/13/20240426287843.pdf</DATEINAME><FORMAT>PDF:1.4</FORMAT></ARTIKEL_IMAGE><ARTIKEL_IMAGE2><DATEINAME></DATEINAME></ARTIKEL_IMAGE2><MEHRZWECKFELD_RECHERCHIERBAR></MEHRZWECKFELD_RECHERCHIERBAR><MEHRZWECKFELD_NICHT_RECHERCHR></MEHRZWECKFELD_NICHT_RECHERCHR><MEHRZWECKFELD></MEHRZWECKFELD><TEXTART>Pressespiegel-Artikel</TEXTART><REFESD>20240426</REFESD></METADATEN><INHALT><TITEL><HAUPTTITEL>Erstes Kind da</HAUPTTITEL><SERIENTITEL>Rubrik ARD</SERIENTITEL></TITEL><VOLLTEXT><TEXT>ARD-„Tagesthemen&#34; Moderatorin Aline Abboud (36) ist zum ersten Mal Mutter geworden. Das verkündete die Journalistin bei Instagram, verriet jedoch nicht das Geschlecht. Auch wer der Vater ist, behält die gebürtige Berlinerin für sich. Seit Januar wird sie bei den „Tagesthemen&#34; von Julia-Niharika Sen (56) vertreten.</TEXT><ANZAHL_WORTE>48</ANZAHL_WORTE></VOLLTEXT><AUTOABSTRACT>ARD-„Tagesthemen&#34;-Moderatorin Aline Abboud (36) ist zum ersten Mal Mutter geworden. Das verkündete die Journalistin bei lnstagram, verriet jedoch nicht das Geschlecht. Auch wer der Vater ist, behält die gebürtige Berlinerin für sich. Seit Januar</AUTOABSTRACT><RUBRIK>ARD</RUBRIK><POSNR>32</POSNR><MELDUNGLISTE><MELDUNG><RUBRIK>ARD</RUBRIK><POSNR>32</POSNR></MELDUNG></MELDUNGLISTE></INHALT></ARTIKEL>